Metadata-Version: 2.1
Name: ynab-client
Version: 0.1.8
Summary: YNAB API v1 Python Client
Home-page: https://github.com/gchiam/ynab-client-python
Author: Gordon Chiam
Author-email: gordon.chiam@gmail.com
License: Apache2
Platform: UNKNOWN
Classifier: Development Status :: 4 - Beta
Classifier: Intended Audience :: Developers
Classifier: License :: OSI Approved :: Apache Software License
Classifier: Programming Language :: Python :: 2
Classifier: Programming Language :: Python :: 3
Classifier: Operating System :: OS Independent
Requires-Dist: urllib3 (>=1.15)
Requires-Dist: six (>=1.10)
Requires-Dist: certifi
Requires-Dist: python-dateutil
